rcl/__init__.py
rcl/__init__.pyi
rcl/py.typed
rcl/rcl.abi3.so
rcl_lang-0.12.0.dist-info/METADATA
rcl_lang-0.12.0.dist-info/WHEEL
rcl_lang-0.12.0.dist-info/RECORD
