Metadata-Version: 2.4
Name: rcl-lang
Version: 0.12.0
Classifier: Development Status :: 4 - Beta
Classifier: License :: OSI Approved :: Apache Software License
Classifier: Programming Language :: Python :: 3.10
Classifier: Programming Language :: Python :: 3.11
Classifier: Programming Language :: Python :: 3.12
Classifier: Programming Language :: Python :: 3.13
Classifier: Topic :: File Formats :: JSON
Classifier: Typing :: Typed
Classifier: Intended Audience :: Developers
Classifier: Intended Audience :: System Administrators
Summary: Python bindings to the RCL configuration language.
Keywords: configuration,configuration language,rcl,json,toml,yaml
Author-email: Ruud van Asseldonk <dev+pypi@veniogames.com>
Maintainer-email: Ruud van Asseldonk <dev+pypi@veniogames.com>
License-Expression: Apache-2.0
Requires-Python: >=3.10
Project-URL: Changelog, https://docs.ruuda.nl/rcl/changelog/
Project-URL: Codeberg, https://codeberg.org/ruuda/rcl
Project-URL: Documentation, https://docs.ruuda.nl/rcl/python_bindings/
Project-URL: GitHub, https://github.com/ruuda/rcl
Project-URL: Homepage, https://rcl-lang.org/
